<Envio>
	<ModeloDocumento>NFSE</ModeloDocumento>
	<Versao>1.00</Versao>
	<RPS>
		<RPSNumero>97</RPSNumero>
		<RPSSerie>1</RPSSerie>
		<RPSTipo>1</RPSTipo>
		<dEmis>2026-02-12T09:12:40</dEmis>
		<dCompetencia>2026-02-12T00:00:00</dCompetencia>
		<LocalPrestServ/>
		<natOp>1</natOp>
		<Operacao/>
		<NumProcesso/>
		<benefIdNac/>
		<benefNumero/>
		<RegEspTrib/>
		<OptSN>2</OptSN>
		<regApTribSN/>
		<IncCult>2</IncCult>
		<tpImunidade/>
		<tpSusp/>
		<Status>1</Status>
		<cVerificaRPS/>
		<EmpreitadaGlobal/>
		<tpAmb>1</tpAmb>
		<finNFSe>0</finNFSe>
		<indFinal>1</indFinal>
		<cIndOp>050101</cIndOp>
		<tpEnteGov/>
		<xTpEnteGov/>
		<indDest/>
		<tpOper/>
		<indDoacao/>
		<indZFMALC/>
		<NFSOutrasinformacoes/>
		<cMotivoEmisTI/>
		<chNFSeRej/>
		<RPSCanhoto/>
		<Arquivo/>
		<ExtensaoArquivo/>
		<RPSSubs>
			<SubsNumero/>
			<SubsSerie/>
			<SubsTipo/>
			<SubsNFSeNumero/>
			<SubsDEmisNFSe/>
			<SubsChave/>
			<SubsCodMotivo/>
			<SubsDescMotivo/>
		</RPSSubs>
		<Prestador>
			<CNPJ_prest>00000000000000</CNPJ_prest>
			<xNome>EMPRESA EXEMPLO LTDA</xNome>
			<xFant>EMPRESA EXEMPLO FILIAL</xFant>
			<IM/>
			<IE>0000000000</IE>
			<CMC/>
			<CAEPF/>
			<enderPrest>
				<TPEnd>RUA</TPEnd>
				<xLgr>RUA EXEMPLO</xLgr>
				<nro>100</nro>
				<xCpl/>
				<xBairro>CENTRO</xBairro>
				<cMun>4307005</cMun>
				<UF>RS</UF>
				<CEP>99700000</CEP>
				<fone>00000000000</fone>
				<Email>contato@exemplo.com.br</Email>
			</enderPrest>
		</Prestador>
		<ListaItens>
			<Item>
				<ItemSeq>1</ItemSeq>
				<ItemCod>5002</ItemCod>
				<ItemDesc>SERVIÇO EXEMPLO 1</ItemDesc>
				<ItemQtde>1</ItemQtde>
				<ItemvUnit>150</ItemvUnit>
				<ItemuMed>UN</ItemuMed>
				<ItemvlDed/>
				<ItemTributavel>S</ItemTributavel>
				<ItemcCnae/>
				<ItemTributMunicipio/>
				<ItemnAlvara/>
				<ItemvIss>4.5</ItemvIss>
				<ItemvDesconto/>
				<ItemAliquota>3.000000</ItemAliquota>
				<ItemVlrTotal>150</ItemVlrTotal>
				<ItemBaseCalculo>150</ItemBaseCalculo>
				<ItemvlrISSRetido/>
				<ItemIssRetido>2</ItemIssRetido>
				<ItemRespRetencao/>
				<ItemIteListServico>14.01</ItemIteListServico>
				<itemCodTributNacional>140101</itemCodTributNacional>
				<ItemExigibilidadeISS>1</ItemExigibilidadeISS>
				<ItemcMunIncidencia>4307005</ItemcMunIncidencia>
				<ItemNumProcesso/>
				<ItemDedTipo/>
				<ItemDedCPFRef/>
				<ItemDedCNPJRef/>
				<ItemDedNFRef/>
				<ItemDedvlTotRef/>
				<ItemDedPer/>
				<ItemDedValor/>
				<ItemVlrLiquido>150</ItemVlrLiquido>
				<ItemValAliqINSS>0.0000</ItemValAliqINSS>
				<ItemValINSS/>
				<ItemValBCINSS/>
				<ItemValAliqIR>0.0000</ItemValAliqIR>
				<ItemValIR/>
				<ItemValBCIRRF/>
				<ItemValAliqCOFINS>0.0000</ItemValAliqCOFINS>
				<ItemValCOFINS/>
				<ItemValBCCOFINS/>
				<ItemValAliqCSLL>0.0000</ItemValAliqCSLL>
				<ItemValCSLL/>
				<ItemValBCCSLL/>
				<ItemValAliqPIS>0.0000</ItemValAliqPIS>
				<ItemValPIS/>
				<ItemValBCPIS/>
				<ItemRedBC/>
				<ItemRedBCRetido/>
				<ItemBCRetido/>
				<ItemValAliqISSRetido>0.0000</ItemValAliqISSRetido>
				<ItemPaisImpDevido>BR</ItemPaisImpDevido>
				<ItemCST/>
				<ItemJustDed/>
				<ItemvOutrasRetencoes/>
				<ItemDescIncondicionado/>
				<ItemDescCondicionado/>
				<ItemTotalAproxTribServ/>
				<ItemDescHospedagem/>
				<ItemQtdeHospedes/>
				<ItemQtdeDiariasHospedagem/>
				<ItemCodQuartoHospedagem/>
				<ItemDtaEntrHospedagem/>
				<ItemDtaSaiHospedagem/>
				<ItemValorDiariaHospedagem/>
				<ItemCSTPisCofins>08</ItemCSTPisCofins>
				<ItemTpRetPisCofins/>
				<ItemNBS>1.2001.31.10</ItemNBS>
			</Item>
		</ListaItens>
		<ListaParcelas>
			<Parcela>
				<PrcSequencial>1</PrcSequencial>
				<PrcValor>350</PrcValor>
				<PrcDtaVencimento>2026-12-02T00:00:00</PrcDtaVencimento>
				<PrcNroFatura/>
				<PrcTipVenc>4</PrcTipVenc>
				<PrcDscTipVenc>Outros</PrcDscTipVenc>
				<PrcValLiquido>350</PrcValLiquido>
				<PrcValDesconto/>
			</Parcela>
		</ListaParcelas>
		<Servico>
			<IteListServico>140101</IteListServico>
			<Cnae/>
			<fPagamento/>
			<tpag/>
			<codTributNacional>140101</codTributNacional>
			<TributMunicipio/>
			<TributMunicDesc>SERVIÇOS DIVERSOS</TributMunicDesc>
			<Discriminacao>SERVIÇO EXEMPLO 1 SERVIÇO EXEMPLO 2</Discriminacao>
			<cMun>4307005</cMun>
			<SerQuantidade>2</SerQuantidade>
			<SerUnidade>HR</SerUnidade>
			<SerNumAlvara/>
			<PaiPreServico>BR</PaiPreServico>
			<cMunIncidencia>4307005</cMunIncidencia>
			<dVencimento/>
			<ObsInsPagamento/>
			<ObrigoMunic/>
			<TributacaoISS/>
			<CodigoAtividadeEconomica/>
			<ServicoViasPublicas>2</ServicoViasPublicas>
			<NumeroParcelas/>
			<NroOrcamento/>
			<CodigoNBS>120013110</CodigoNBS>
			<docRef/>
			<idDocTec/>
			<CST>08</CST>
			<Valores>
				<ValServicos>350</ValServicos>
				<ValPercDeducoes/>
				<ValDeducoes/>
				<ValOutrasDeducoes/>
				<ValPIS/>
				<ValBCPIS/>
				<ValCOFINS/>
				<ValBCCOFINS/>
				<ValINSS/>
				<ValBCINSS/>
				<ValIR/>
				<ValBCIRRF/>
				<ValCSLL/>
				<ValBCCSLL/>
				<RespRetencao/>
				<Tributavel>S</Tributavel>
				<ValISS>10.50</ValISS>
				<ISSRetido>2</ISSRetido>
				<ValISSRetido/>
				<ValTotal>350</ValTotal>
				<ValTotalRecebido>350</ValTotalRecebido>
				<ValBaseCalculo>350.00</ValBaseCalculo>
				<ValOutrasRetencoes/>
				<ValAliqISS>3.0000</ValAliqISS>
				<ValAliqPIS>0.0000</ValAliqPIS>
				<PISRetido/>
				<ValAliqCOFINS>0.0000</ValAliqCOFINS>
				<COFINSRetido/>
				<ValAliqIR>0.0000</ValAliqIR>
				<IRRetido>2</IRRetido>
				<ValAliqCSLL>0.0000</ValAliqCSLL>
				<CSLLRetido>2</CSLLRetido>
				<ValAliqINSS>0.0000</ValAliqINSS>
				<INSSRetido>2</INSSRetido>
				<ValAliqCpp/>
				<CppRetido>2</CppRetido>
				<ValCpp/>
				<OutrasRetencoesRetido>2</OutrasRetencoesRetido>
				<ValBCOutrasRetencoes/>
				<ValAliqOutrasRetencoes/>
				<ValAliqTotTributos/>
				<ValLiquido>350.00</ValLiquido>
				<ValDescIncond/>
				<ValDescCond/>
				<ValAcrescimos/>
				<ValAliqISSoMunic>0.0000</ValAliqISSoMunic>
				<InfValPIS/>
				<InfValCOFINS/>
				<ValLiqFatura/>
				<ValBCISSRetido/>
				<NroFatura/>
				<CargaTribValor/>
				<CargaTribPercentual/>
				<CargaTribFonte/>
				<JustDed/>
				<ValCredito/>
				<OutrosImp/>
				<ValRedBC/>
				<ValRetFederais/>
				<ValAproxTrib/>
				<NroDeducao/>
				<mdPrestacao/>
				<vincPrest/>
				<tpMoeda/>
				<ValServEst/>
				<mecAFComexP/>
				<mecAFComexT/>
				<movTempBens/>
				<nDI/>
				<nRE/>
				<mdic/>
				<vRecebInterm/>
				<ValRedBenef/>
				<PercRedBenef/>
				<ValRetEstaduais/>
				<ValRetMunicipais/>
				<ValAliqRetFederais/>
				<ValAliqRetEstaduais/>
				<ValAliqRetMunicipais/>
				<ValAproxTribAliqSN/>
				<IBSCBS>
					<ValTotNF>350.00</ValTotNF>
					<ValBCIBSCBS>339.50</ValBCIBSCBS>
					<ValCalcReeRepRes/>
					<ValpRedutor/>
					<ValMulta/>
					<ValJuros/>
					<ValInicialCobrado/>
					<ValFinalCobrado/>
					<ValIPI/>
					<TribRegular>
						<ValpAliqEfeRegIBSUF/>
						<ValTribRegIBSUF/>
						<ValpAliqEfeRegIBSMun/>
						<ValTribRegIBSMun/>
						<ValpAliqEfeRegCBS/>
						<ValTribRegCBS/>
					</TribRegular>
					<TribCompraGov>
						<ValpIBSUF/>
						<ValIBSUF/>
						<ValpIBSMun/>
						<ValIBSMun/>
						<ValpCBS/>
						<ValCBS/>
					</TribCompraGov>
					<IBS>
						<ValIBSTot>0.34</ValIBSTot>
						<ValCredPresIBS/>
						<ValpCredPresIBS/>
						<ValIBSUF>0.34</ValIBSUF>
						<ValpIBSUF>0.10</ValpIBSUF>
						<ValDifUF/>
						<ValpDifUF/>
						<ValTribOpUF/>
						<ValpRedAliqUF/>
						<ValpAliqEfetUF/>
						<ValIBSMun>0.00</ValIBSMun>
						<ValDifMun/>
						<ValpDifMun/>
						<ValDevTribMunIBS/>
						<ValTribOpMun/>
						<ValpAliqEfetMun/>
						<ValpRedAliqMun/>
						<ValpIBSMun>0.00</ValpIBSMun>
						<ValIBSEstCred/>
					</IBS>
					<CBS>
						<ValCBS>3.06</ValCBS>
						<ValpCBS>0.90</ValpCBS>
						<ValCredPresCBS/>
						<ValpCredPresCBS/>
						<ValDifCBS/>
						<ValpDifCBS/>
						<ValpAliqEfetCBS/>
						<ValpRedAliqCBS/>
						<ValCBSEstCred/>
					</CBS>
				</IBSCBS>
			</Valores>
			<LocalPrestacao>
				<SerEndTpLgr>RUA</SerEndTpLgr>
				<SerEndLgr>RUA EXEMPLO</SerEndLgr>
				<SerEndNumero>100</SerEndNumero>
				<SerEndComplemento/>
				<SerEndBairro>CENTRO</SerEndBairro>
				<SerEndxMun>MUNICIPIO EXEMPLO</SerEndxMun>
				<SerEndcMun>4307005</SerEndcMun>
				<SerEndCep>99700000</SerEndCep>
				<SerEndSiglaUF>RS</SerEndSiglaUF>
			</LocalPrestacao>
			<IBSCBS>
				<cLocalidadeIncid/>
				<xLocalidadeIncid/>
				<CSTIBSCBS>000</CSTIBSCBS>
				<cClassTrib>000001</cClassTrib>
				<cCredPres/>
				<Onerosidade/>
				<PagParceladoAntecipado/>
				<NCM/>
				<indCompGov/>
				<tpRetPisCofins/>
				<TribRegular>
					<CSTReg/>
					<cClassTribReg/>
				</TribRegular>
			</IBSCBS>
		</Servico>
		<Tomador>
			<TomaCNPJ/>
			<TomaCPF>00000000000</TomaCPF>
			<TomaIE>ISENTO</TomaIE>
			<TomaIM/>
			<TomaRazaoSocial>CLIENTE EXEMPLO</TomaRazaoSocial>
			<TomatpLgr>RUA</TomatpLgr>
			<TomaEndereco>RUA EXEMPLO TOMADOR</TomaEndereco>
			<TomaNumero>100</TomaNumero>
			<TomaComplemento/>
			<TomaBairro>BAIRRO EXEMPLO</TomaBairro>
			<TomacMun>4307005</TomacMun>
			<TomaxMun>MUNICIPIO EXEMPLO</TomaxMun>
			<TomaUF>RS</TomaUF>
			<TomaPais>BR</TomaPais>
			<TomaCEP>99700000</TomaCEP>
			<TomaTelefone>00000000000</TomaTelefone>
			<TomaTipoTelefone/>
			<TomaEmail/>
			<TomaSite/>
			<TomaIME/>
			<TomaSituacaoEspecial/>
			<DocTomadorEstrangeiro/>
			<TomaRegEspTrib/>
			<TomaCadastroMunicipio/>
			<TomaOrgaoPublico/>
			<TomaEnderecoInformado/>
			<TomaCAEPF/>
			<TomaExSemNIF/>
		</Tomador>
		<IntermServico>
			<IntermRazaoSocial/>
			<IntermCNPJ/>
			<IntermCPF/>
			<IntermNIF/>
			<IntermExSemNIF/>
			<IntermIM/>
			<IntermEmail/>
			<IntermEndereco/>
			<IntermNumero/>
			<IntermComplemento/>
			<IntermBairro/>
			<IntermCep/>
			<IntermCmun/>
			<IntermXmun/>
			<IntermFone/>
			<IntermIE/>
			<IntermPais/>
			<IntermUF/>
			<IntermCAEPF/>
		</IntermServico>
		<ConstCivil>
			<CodObra/>
			<Art/>
			<ObraLog/>
			<ObraCompl/>
			<ObraNumero/>
			<ObraBairro/>
			<ObraCEP/>
			<ObraMun/>
			<ObraUF/>
			<ObraPais/>
			<ObraCEI/>
			<ObraMatricula/>
			<ObraValRedBC/>
			<ObraTipo/>
			<ObraNomeFornecedor/>
			<ObraNumeroNF/>
			<ObraDataNF/>
			<ObraNumEncapsulamento/>
			<AbatimentoMateriais/>
			<ObraXMun/>
			<ObraDesc/>
			<ObraCIB/>
			<ObraInscImobFis/>
			<ObraCPFNF/>
			<ObraCNPJNF/>
			<ListaMaterial/>
		</ConstCivil>
		<ListaDed/>
		<Transportadora>
			<TraNome/>
			<TraCPFCNPJ/>
			<TraIE/>
			<TraPlaca/>
			<TraEnd/>
			<TraMun/>
			<TraUF/>
			<TraPais/>
			<TraTipoFrete/>
		</Transportadora>
		<Locacao>
			<categServ/>
			<objetoLocacao/>
			<extensaoFerrovia/>
			<nPostes/>
		</Locacao>
		<AtividadeEvento>
			<AtivDesc/>
			<AtivDataInicial/>
			<AtivDataFinal/>
			<AtivIdEvento/>
			<AtivEndLogradouro/>
			<AtivEndNumero/>
			<AtivEndCompl/>
			<AtivEndBairro/>
			<AtivEndCEP/>
			<AtivEndcMun/>
			<AtivEndxMun/>
			<AtivEndUf/>
		</AtividadeEvento>
		<Pedagio>
			<PedCategVeiculo/>
			<PednEixos/>
			<PedRodagem/>
			<PedSentido/>
			<PedPlaca/>
			<PedCodAcesso/>
			<PedCodContrato/>
		</Pedagio>
		<Destinatario>
			<DestCNPJ/>
			<DestCPF/>
			<DestNIF/>
			<DestcNaoNIF/>
			<DestNome/>
			<DestEndereco/>
			<DestNumero/>
			<DestComplemento/>
			<DestBairro/>
			<DestFone/>
			<DestEmail/>
			<DestcMun/>
			<DestxMun/>
			<DestCEP/>
			<DestPais/>
			<DestEstProvReg/>
		</Destinatario>
		<Imovel>
			<ImovInscImobFisc/>
			<ImovCIB/>
			<ImovCEP/>
			<ImovEndereco/>
			<ImovNumero/>
			<ImovComplemento/>
			<ImovBairro/>
			<ImovxMun/>
			<ImovEstProvReg/>
		</Imovel>
		<ListaBensMoveis/>
		<ListaDedIBSCBS/>
		<ListaNFSeRefPagAntecipado/>
	</RPS>
</Envio>